[
  {
    "rating": {
      "max": 10,
      "average": 3.4,
      "details": {
        "1": 264.0,
        "3": 75.0,
        "2": 146.0,
        "5": 5.0,
        "4": 13.0
      },
      "stars": "20",
      "min": 0
    },
    "genres": [
      "喜剧"
    ],
    "title": "人间·喜剧",
    "casts": [
      {
        "avatars": {
          "small": "https://img3.doubanio.com/view/celebrity/s_ratio_celebrity/public/p1437031126.82.jpg",
          "large": "https://img3.doubanio.com/view/celebrity/s_ratio_celebrity/public/p1437031126.82.jpg",
          "medium": "https://img3.doubanio.com/view/celebrity/s_ratio_celebrity/public/p1437031126.82.jpg"
        },
        "name_en": "Allen",
        "name": "艾伦",
        "alt": "https://movie.douban.com/celebrity/1350408/",
        "id": "1350408"
      },
      {
        "avatars": {
          "small": "https://img3.doubanio.com/view/celebrity/s_ratio_celebrity/public/p1443582361.31.jpg",
          "large": "https://img3.doubanio.com/view/celebrity/s_ratio_celebrity/public/p1443582361.31.jpg",
          "medium": "https://img3.doubanio.com/view/celebrity/s_ratio_celebrity/public/p1443582361.31.jpg"
        },
        "name_en": "Zhi Wang",
        "name": "王智",
        "alt": "https://movie.douban.com/celebrity/1321587/",
        "id": "1321587"
      },
      {
        "avatars": {
          "small": "https://img3.doubanio.com/view/celebrity/s_ratio_celebrity/public/p50150.jpg",
          "large": "https://img3.doubanio.com/view/celebrity/s_ratio_celebrity/public/p50150.jpg",
          "medium": "https://img3.doubanio.com/view/celebrity/s_ratio_celebrity/public/p50150.jpg"
        },
        "name_en": "Nuo Lu",
        "name": "鲁诺",
        "alt": "https://movie.douban.com/celebrity/1321098/",
        "id": "1321098"
      }
    ],
    "durations": [
      "90分钟"
    ],
    "collect_count": 5943,
    "mainland_pubdate": "2019-03-29",
    "has_video": false,
    "original_title": "人间·喜剧",
    "subtype": "movie",
    "directors": [
      {
        "avatars": {
          "small": "https://img1.doubanio.com/view/celebrity/s_ratio_celebrity/public/p35187.jpg",
          "large": "https://img1.doubanio.com/view/celebrity/s_ratio_celebrity/public/p35187.jpg",
          "medium": "https://img1.doubanio.com/view/celebrity/s_ratio_celebrity/public/p35187.jpg"
        },
        "name_en": "Zhou Sun",
        "name": "孙周",
        "alt": "https://movie.douban.com/celebrity/1298649/",
        "id": "1298649"
      }
    ],
    "pubdates": [
      "2019-03-29(中国大陆)"
    ],
    "year": "2019",
    "images": {
      "small": "https://img3.doubanio.com/view/photo/s_ratio_poster/public/p2551693460.jpg",
      "large": "https://img3.doubanio.com/view/photo/s_ratio_poster/public/p2551693460.jpg",
      "medium": "https://img3.doubanio.com/view/photo/s_ratio_poster/public/p2551693460.jpg"
    },
    "alt": "https://movie.douban.com/subject/27179414/",
    "id": "27179414"
  },
  {
    "rating": {
      "max": 10,
      "average": 7.8,
      "details": {
        "1": 45.0,
        "3": 3511.0,
        "2": 332.0,
        "5": 2796.0,
        "4": 7035.0
      },
      "stars": "40",
      "min": 0
    },
    "genres": [
      "科幻",
      "悬疑",
      "惊悚"
    ],
    "title": "海市蜃楼",
    "casts": [
      {
        "avatars": {
          "small": "https://img3.doubanio.com/view/celebrity/s_ratio_celebrity/public/p46101.jpg",
          "large": "https://img3.doubanio.com/view/celebrity/s_ratio_celebrity/public/p46101.jpg",
          "medium": "https://img3.doubanio.com/view/celebrity/s_ratio_celebrity/public/p46101.jpg"
        },
        "name_en": "Adriana Ugarte",
        "name": "阿德里亚娜·乌加特",
        "alt": "https://movie.douban.com/celebrity/1014538/",
        "id": "1014538"
      },
      {
        "avatars": {
          "small": "https://img1.doubanio.com/view/celebrity/s_ratio_celebrity/public/p1490764328.09.jpg",
          "large": "https://img1.doubanio.com/view/celebrity/s_ratio_celebrity/public/p1490764328.09.jpg",
          "medium": "https://img1.doubanio.com/view/celebrity/s_ratio_celebrity/public/p1490764328.09.jpg"
        },
        "name_en": "Chino Darín",
        "name": "奇诺·达林",
        "alt": "https://movie.douban.com/celebrity/1344260/",
        "id": "1344260"
      },
      {
        "avatars": {
          "small": "https://img3.doubanio.com/view/celebrity/s_ratio_celebrity/public/pnqeO8jPqetocel_avatar_uploaded1525297233.62.jpg",
          "large": "https://img3.doubanio.com/view/celebrity/s_ratio_celebrity/public/pnqeO8jPqetocel_avatar_uploaded1525297233.62.jpg",
          "medium": "https://img3.doubanio.com/view/celebrity/s_ratio_celebrity/public/pnqeO8jPqetocel_avatar_uploaded1525297233.62.jpg"
        },
        "name_en": "Álvaro Morte",
        "name": "阿尔瓦罗·莫奇",
        "alt": "https://movie.douban.com/celebrity/1392255/",
        "id": "1392255"
      }
    ],
    "durations": [
      "128分钟"
    ],
    "collect_count": 68494,
    "mainland_pubdate": "2019-03-28",
    "has_video": false,
    "original_title": "Durante la tormenta",
    "subtype": "movie",
    "directors": [
      {
        "avatars": {
          "small": "https://img1.doubanio.com/view/celebrity/s_ratio_celebrity/public/p1490063334.69.jpg",
          "large": "https://img1.doubanio.com/view/celebrity/s_ratio_celebrity/public/p1490063334.69.jpg",
          "medium": "https://img1.doubanio.com/view/celebrity/s_ratio_celebrity/public/p1490063334.69.jpg"
        },
        "name_en": "Oriol Paulo",
        "name": "奥里奥尔·保罗",
        "alt": "https://movie.douban.com/celebrity/1323799/",
        "id": "1323799"
      }
    ],
    "pubdates": [
      "2018-11-30(西班牙)",
      "2019-03-28(中国大陆)"
    ],
    "year": "2018",
    "images": {
      "small": "https://img3.doubanio.com/view/photo/s_ratio_poster/public/p2551172384.jpg",
      "large": "https://img3.doubanio.com/view/photo/s_ratio_poster/public/p2551172384.jpg",
      "medium": "https://img3.doubanio.com/view/photo/s_ratio_poster/public/p2551172384.jpg"
    },
    "alt": "https://movie.douban.com/subject/30164448/",
    "id": "30164448"
  },
  {
    "rating": {
      "max": 10,
      "average": 4.8,
      "details": {
        "1": 1506.0,
        "3": 2012.0,
        "2": 1987.0,
        "5": 247.0,
        "4": 589.0
      },
      "stars": "25",
      "min": 0
    },
    "genres": [
      "爱情"
    ],
    "title": "比悲伤更悲伤的故事",
    "casts": [
      {
        "avatars": {
          "small": "https://img3.doubanio.com/view/celebrity/s_ratio_celebrity/public/p31663.jpg",
          "large": "https://img3.doubanio.com/view/celebrity/s_ratio_celebrity/public/p31663.jpg",
          "medium": "https://img3.doubanio.com/view/celebrity/s_ratio_celebrity/public/p31663.jpg"
        },
        "name_en": "Ivy Chen",
        "name": "陈意涵",
        "alt": "https://movie.douban.com/celebrity/1274316/",
        "id": "1274316"
      },
      {
        "avatars": {
          "small": "https://img1.doubanio.com/view/celebrity/s_ratio_celebrity/public/p1511061580.88.jpg",
          "large": "https://img1.doubanio.com/view/celebrity/s_ratio_celebrity/public/p1511061580.88.jpg",
          "medium": "https://img1.doubanio.com/view/celebrity/s_ratio_celebrity/public/p1511061580.88.jpg"
        },
        "name_en": "Jasper Liu",
        "name": "刘以豪",
        "alt": "https://movie.douban.com/celebrity/1326546/",
        "id": "1326546"
      },
      {
        "avatars": {
          "small": "https://img1.doubanio.com/view/celebrity/s_ratio_celebrity/public/p31369.jpg",
          "large": "https://img1.doubanio.com/view/celebrity/s_ratio_celebrity/public/p31369.jpg",
          "medium": "https://img1.doubanio.com/view/celebrity/s_ratio_celebrity/public/p31369.jpg"
        },
        "name_en": "Bryan Shu-Hao Chang",
        "name": "张书豪",
        "alt": "https://movie.douban.com/celebrity/1315045/",
        "id": "1315045"
      }
    ],
    "durations": [
      "105分钟"
    ],
    "collect_count": 69536,
    "mainland_pubdate": "2019-03-14",
    "has_video": false,
    "original_title": "比悲傷更悲傷的故事",
    "subtype": "movie",
    "directors": [
      {
        "avatars": {
          "small": "https://img1.doubanio.com/view/celebrity/s_ratio_celebrity/public/p44818.jpg",
          "large": "https://img1.doubanio.com/view/celebrity/s_ratio_celebrity/public/p44818.jpg",
          "medium": "https://img1.doubanio.com/view/celebrity/s_ratio_celebrity/public/p44818.jpg"
        },
        "name_en": "Hsiao Chien Lin",
        "name": "林孝谦",
        "alt": "https://movie.douban.com/celebrity/1312860/",
        "id": "1312860"
      }
    ],
    "pubdates": [
      "2018-11-30(台湾)",
      "2019-03-14(中国大陆)"
    ],
    "year": "2018",
    "images": {
      "small": "https://img3.doubanio.com/view/photo/s_ratio_poster/public/p2549523952.jpg",
      "large": "https://img3.doubanio.com/view/photo/s_ratio_poster/public/p2549523952.jpg",
      "medium": "https://img3.doubanio.com/view/photo/s_ratio_poster/public/p2549523952.jpg"
    },
    "alt": "https://movie.douban.com/subject/27624661/",
    "id": "27624661"
  },
  {
    "rating": {
      "max": 10,
      "average": 6.8,
      "details": {
        "1": 24.0,
        "3": 1478.0,
        "2": 284.0,
        "5": 305.0,
        "4": 950.0
      },
      "stars": "35",
      "min": 0
    },
    "genres": [
      "奇幻",
      "冒险"
    ],
    "title": "小飞象",
    "casts": [
      {
        "avatars": {
          "small": "https://img1.doubanio.com/view/celebrity/s_ratio_celebrity/public/p36438.jpg",
          "large": "https://img1.doubanio.com/view/celebrity/s_ratio_celebrity/public/p36438.jpg",
          "medium": "https://img1.doubanio.com/view/celebrity/s_ratio_celebrity/public/p36438.jpg"
        },
        "name_en": "Eva Green",
        "name": "伊娃·格林",
        "alt": "https://movie.douban.com/celebrity/1025155/",
        "id": "1025155"
      },
      {
        "avatars": {
          "small": "https://img3.doubanio.com/view/celebrity/s_ratio_celebrity/public/p724.jpg",
          "large": "https://img3.doubanio.com/view/celebrity/s_ratio_celebrity/public/p724.jpg",
          "medium": "https://img3.doubanio.com/view/celebrity/s_ratio_celebrity/public/p724.jpg"
        },
        "name_en": "Colin Farrell",
        "name": "科林·法瑞尔",
        "alt": "https://movie.douban.com/celebrity/1084255/",
        "id": "1084255"
      },
      {
        "avatars": {
          "small": "https://img3.doubanio.com/view/celebrity/s_ratio_celebrity/public/p1420615848.64.jpg",
          "large": "https://img3.doubanio.com/view/celebrity/s_ratio_celebrity/public/p1420615848.64.jpg",
          "medium": "https://img3.doubanio.com/view/celebrity/s_ratio_celebrity/public/p1420615848.64.jpg"
        },
        "name_en": "Michael Keaton",
        "name": "迈克尔·基顿",
        "alt": "https://movie.douban.com/celebrity/1049486/",
        "id": "1049486"
      }
    ],
    "durations": [
      "112分钟"
    ],
    "collect_count": 13473,
    "mainland_pubdate": "2019-03-29",
    "has_video": false,
    "original_title": "Dumbo",
    "subtype": "movie",
    "directors": [
      {
        "avatars": {
          "small": "https://img3.doubanio.com/view/celebrity/s_ratio_celebrity/public/p44690.jpg",
          "large": "https://img3.doubanio.com/view/celebrity/s_ratio_celebrity/public/p44690.jpg",
          "medium": "https://img3.doubanio.com/view/celebrity/s_ratio_celebrity/public/p44690.jpg"
        },
        "name_en": "Tim Burton",
        "name": "蒂姆·波顿",
        "alt": "https://movie.douban.com/celebrity/1019002/",
        "id": "1019002"
      }
    ],
    "pubdates": [
      "2019-03-29(美国)",
      "2019-03-29(中国大陆)"
    ],
    "year": "2019",
    "images": {
      "small": "https://img3.doubanio.com/view/photo/s_ratio_poster/public/p2549234765.jpg",
      "large": "https://img3.doubanio.com/view/photo/s_ratio_poster/public/p2549234765.jpg",
      "medium": "https://img3.doubanio.com/view/photo/s_ratio_poster/public/p2549234765.jpg"
    },
    "alt": "https://movie.douban.com/subject/25924056/",
    "id": "25924056"
  },
  {
    "rating": {
      "max": 10,
      "average": 6.8,
      "details": {
        "1": 102.0,
        "3": 1437.0,
        "2": 379.0,
        "5": 410.0,
        "4": 1182.0
      },
      "stars": "35",
      "min": 0
    },
    "genres": [
      "剧情"
    ],
    "title": "老师·好",
    "casts": [
      {
        "avatars": {
          "small": "https://img3.doubanio.com/view/celebrity/s_ratio_celebrity/public/p1504169127.76.jpg",
          "large": "https://img3.doubanio.com/view/celebrity/s_ratio_celebrity/public/p1504169127.76.jpg",
          "medium": "https://img3.doubanio.com/view/celebrity/s_ratio_celebrity/public/p1504169127.76.jpg"
        },
        "name_en": "Qian Yu",
        "name": "于谦",
        "alt": "https://movie.douban.com/celebrity/1274307/",
        "id": "1274307"
      },
      {
        "avatars": {
          "small": "https://img3.doubanio.com/view/celebrity/s_ratio_celebrity/public/p1442330240.0.jpg",
          "large": "https://img3.doubanio.com/view/celebrity/s_ratio_celebrity/public/p1442330240.0.jpg",
          "medium": "https://img3.doubanio.com/view/celebrity/s_ratio_celebrity/public/p1442330240.0.jpg"
        },
        "name_en": "Melody Tang",
        "name": "汤梦佳",
        "alt": "https://movie.douban.com/celebrity/1351587/",
        "id": "1351587"
      },
      {
        "avatars": {
          "small": "https://img3.doubanio.com/view/celebrity/s_ratio_celebrity/public/p1542251128.4.jpg",
          "large": "https://img3.doubanio.com/view/celebrity/s_ratio_celebrity/public/p1542251128.4.jpg",
          "medium": "https://img3.doubanio.com/view/celebrity/s_ratio_celebrity/public/p1542251128.4.jpg"
        },
        "name_en": "Guangyuan Wang",
        "name": "王广源",
        "alt": "https://movie.douban.com/celebrity/1403828/",
        "id": "1403828"
      }
    ],
    "durations": [
      "111分钟"
    ],
    "collect_count": 28006,
    "mainland_pubdate": "2019-03-22",
    "has_video": false,
    "original_title": "老师·好",
    "subtype": "movie",
    "directors": [
      {
        "avatars": {
          "small": "https://img3.doubanio.com/view/celebrity/s_ratio_celebrity/public/p1550730545.46.jpg",
          "large": "https://img3.doubanio.com/view/celebrity/s_ratio_celebrity/public/p1550730545.46.jpg",
          "medium": "https://img3.doubanio.com/view/celebrity/s_ratio_celebrity/public/p1550730545.46.jpg"
        },
        "name_en": "Luan Zhang",
        "name": "张栾",
        "alt": "https://movie.douban.com/celebrity/1383594/",
        "id": "1383594"
      }
    ],
    "pubdates": [
      "2019-03-22(中国大陆)"
    ],
    "year": "2019",
    "images": {
      "small": "https://img1.doubanio.com/view/photo/s_ratio_poster/public/p2551352209.jpg",
      "large": "https://img1.doubanio.com/view/photo/s_ratio_poster/public/p2551352209.jpg",
      "medium": "https://img1.doubanio.com/view/photo/s_ratio_poster/public/p2551352209.jpg"
    },
    "alt": "https://movie.douban.com/subject/27663742/",
    "id": "27663742"
  },
  {
    "rating": {
      "max": 10,
      "average": 7.0,
      "details": {
        "1": 507.0,
        "3": 23217.0,
        "2": 3199.0,
        "5": 5311.0,
        "4": 18475.0
      },
      "stars": "35",
      "min": 0
    },
    "genres": [
      "动作",
      "科幻",
      "冒险"
    ],
    "title": "惊奇队长",
    "casts": [
      {
        "avatars": {
          "small": "https://img3.doubanio.com/view/celebrity/s_ratio_celebrity/public/p1392029372.12.jpg",
          "large": "https://img3.doubanio.com/view/celebrity/s_ratio_celebrity/public/p1392029372.12.jpg",
          "medium": "https://img3.doubanio.com/view/celebrity/s_ratio_celebrity/public/p1392029372.12.jpg"
        },
        "name_en": "Brie Larson",
        "name": "布丽·拉尔森",
        "alt": "https://movie.douban.com/celebrity/1027194/",
        "id": "1027194"
      },
      {
        "avatars": {
          "small": "https://img3.doubanio.com/view/celebrity/s_ratio_celebrity/public/p4952.jpg",
          "large": "https://img3.doubanio.com/view/celebrity/s_ratio_celebrity/public/p4952.jpg",
          "medium": "https://img3.doubanio.com/view/celebrity/s_ratio_celebrity/public/p4952.jpg"
        },
        "name_en": "Jude Law",
        "name": "裘德·洛",
        "alt": "https://movie.douban.com/celebrity/1010510/",
        "id": "1010510"
      },
      {
        "avatars": {
          "small": "https://img3.doubanio.com/view/celebrity/s_ratio_celebrity/public/p1365913316.45.jpg",
          "large": "https://img3.doubanio.com/view/celebrity/s_ratio_celebrity/public/p1365913316.45.jpg",
          "medium": "https://img3.doubanio.com/view/celebrity/s_ratio_celebrity/public/p1365913316.45.jpg"
        },
        "name_en": "Samuel L. Jackson",
        "name": "塞缪尔·杰克逊",
        "alt": "https://movie.douban.com/celebrity/1054408/",
        "id": "1054408"
      }
    ],
    "durations": [
      "124分钟"
    ],
    "collect_count": 286344,
    "mainland_pubdate": "2019-03-08",
    "has_video": false,
    "original_title": "Captain Marvel",
    "subtype": "movie",
    "directors": [
      {
        "avatars": {
          "small": "https://img3.doubanio.com/view/celebrity/s_ratio_celebrity/public/p1550139338.75.jpg",
          "large": "https://img3.doubanio.com/view/celebrity/s_ratio_celebrity/public/p1550139338.75.jpg",
          "medium": "https://img3.doubanio.com/view/celebrity/s_ratio_celebrity/public/p1550139338.75.jpg"
        },
        "name_en": "Anna Boden",
        "name": "安娜·波顿",
        "alt": "https://movie.douban.com/celebrity/1306067/",
        "id": "1306067"
      },
      {
        "avatars": {
          "small": "https://img1.doubanio.com/view/celebrity/s_ratio_celebrity/public/p1550139655.99.jpg",
          "large": "https://img1.doubanio.com/view/celebrity/s_ratio_celebrity/public/p1550139655.99.jpg",
          "medium": "https://img1.doubanio.com/view/celebrity/s_ratio_celebrity/public/p1550139655.99.jpg"
        },
        "name_en": "Ryan Fleck",
        "name": "瑞安·弗雷克",
        "alt": "https://movie.douban.com/celebrity/1050201/",
        "id": "1050201"
      }
    ],
    "pubdates": [
      "2019-03-08(美国)",
      "2019-03-08(中国大陆)"
    ],
    "year": "2019",
    "images": {
      "small": "https://img3.doubanio.com/view/photo/s_ratio_poster/public/p2548870813.jpg",
      "large": "https://img3.doubanio.com/view/photo/s_ratio_poster/public/p2548870813.jpg",
      "medium": "https://img3.doubanio.com/view/photo/s_ratio_poster/public/p2548870813.jpg"
    },
    "alt": "https://movie.douban.com/subject/26213252/",
    "id": "26213252"
  },
  {
    "rating": {
      "max": 10,
      "average": 5.1,
      "details": {
        "1": 10.0,
        "3": 31.0,
        "2": 30.0,
        "5": 2.0,
        "4": 10.0
      },
      "stars": "25",
      "min": 0
    },
    "genres": [
      "喜剧",
      "动画",
      "家庭"
    ],
    "title": "精灵怪物：疯狂之旅",
    "casts": [
      {
        "avatars": {
          "small": "https://img3.doubanio.com/view/celebrity/s_ratio_celebrity/public/p24640.jpg",
          "large": "https://img3.doubanio.com/view/celebrity/s_ratio_celebrity/public/p24640.jpg",
          "medium": "https://img3.doubanio.com/view/celebrity/s_ratio_celebrity/public/p24640.jpg"
        },
        "name_en": "Emily Watson",
        "name": "艾米丽·沃森",
        "alt": "https://movie.douban.com/celebrity/1013814/",
        "id": "1013814"
      },
      {
        "avatars": {
          "small": "https://img3.doubanio.com/view/celebrity/s_ratio_celebrity/public/p49155.jpg",
          "large": "https://img3.doubanio.com/view/celebrity/s_ratio_celebrity/public/p49155.jpg",
          "medium": "https://img3.doubanio.com/view/celebrity/s_ratio_celebrity/public/p49155.jpg"
        },
        "name_en": "Jason Isaacs",
        "name": "詹森·艾萨克",
        "alt": "https://movie.douban.com/celebrity/1017916/",
        "id": "1017916"
      },
      {
        "avatars": {
          "small": "https://img3.doubanio.com/view/celebrity/s_ratio_celebrity/public/p982.jpg",
          "large": "https://img3.doubanio.com/view/celebrity/s_ratio_celebrity/public/p982.jpg",
          "medium": "https://img3.doubanio.com/view/celebrity/s_ratio_celebrity/public/p982.jpg"
        },
        "name_en": "Nick Frost",
        "name": "尼克·弗罗斯特",
        "alt": "https://movie.douban.com/celebrity/1000102/",
        "id": "1000102"
      }
    ],
    "durations": [
      "96分钟",
      "93分钟(中国大陆)"
    ],
    "collect_count": 598,
    "mainland_pubdate": "2019-03-29",
    "has_video": false,
    "original_title": "Happy Family",
    "subtype": "movie",
    "directors": [
      {
        "avatars": {
          "small": "https://img1.doubanio.com/view/celebrity/s_ratio_celebrity/public/p1514386079.69.jpg",
          "large": "https://img1.doubanio.com/view/celebrity/s_ratio_celebrity/public/p1514386079.69.jpg",
          "medium": "https://img1.doubanio.com/view/celebrity/s_ratio_celebrity/public/p1514386079.69.jpg"
        },
        "name_en": "Holger Tappe",
        "name": "霍尔格·塔佩",
        "alt": "https://movie.douban.com/celebrity/1307975/",
        "id": "1307975"
      }
    ],
    "pubdates": [
      "2017-08-24(德国)",
      "2019-03-29(中国大陆)"
    ],
    "year": "2017",
    "images": {
      "small": "https://img3.doubanio.com/view/photo/s_ratio_poster/public/p2551444674.jpg",
      "large": "https://img3.doubanio.com/view/photo/s_ratio_poster/public/p2551444674.jpg",
      "medium": "https://img3.doubanio.com/view/photo/s_ratio_poster/public/p2551444674.jpg"
    },
    "alt": "https://movie.douban.com/subject/27042871/",
    "id": "27042871"
  },
  {
    "rating": {
      "max": 10,
      "average": 8.9,
      "details": {
        "1": 124.0,
        "3": 6788.0,
        "2": 346.0,
        "5": 53956.0,
        "4": 39026.0
      },
      "stars": "45",
      "min": 0
    },
    "genres": [
      "剧情",
      "喜剧",
      "传记"
    ],
    "title": "绿皮书",
    "casts": [
      {
        "avatars": {
          "small": "https://img3.doubanio.com/view/celebrity/s_ratio_celebrity/public/p29922.jpg",
          "large": "https://img3.doubanio.com/view/celebrity/s_ratio_celebrity/public/p29922.jpg",
          "medium": "https://img3.doubanio.com/view/celebrity/s_ratio_celebrity/public/p29922.jpg"
        },
        "name_en": "Viggo Mortensen",
        "name": "维果·莫腾森",
        "alt": "https://movie.douban.com/celebrity/1054520/",
        "id": "1054520"
      },
      {
        "avatars": {
          "small": "https://img3.doubanio.com/view/celebrity/s_ratio_celebrity/public/p1488440651.5.jpg",
          "large": "https://img3.doubanio.com/view/celebrity/s_ratio_celebrity/public/p1488440651.5.jpg",
          "medium": "https://img3.doubanio.com/view/celebrity/s_ratio_celebrity/public/p1488440651.5.jpg"
        },
        "name_en": "Mahershala Ali",
        "name": "马赫沙拉·阿里",
        "alt": "https://movie.douban.com/celebrity/1004702/",
        "id": "1004702"
      },
      {
        "avatars": {
          "small": "https://img3.doubanio.com/view/celebrity/s_ratio_celebrity/public/p1405786644.35.jpg",
          "large": "https://img3.doubanio.com/view/celebrity/s_ratio_celebrity/public/p1405786644.35.jpg",
          "medium": "https://img3.doubanio.com/view/celebrity/s_ratio_celebrity/public/p1405786644.35.jpg"
        },
        "name_en": "Linda Cardellini",
        "name": "琳达·卡德里尼",
        "alt": "https://movie.douban.com/celebrity/1010545/",
        "id": "1010545"
      }
    ],
    "durations": [
      "130分钟"
    ],
    "collect_count": 560213,
    "mainland_pubdate": "2019-03-01",
    "has_video": false,
    "original_title": "Green Book",
    "subtype": "movie",
    "directors": [
      {
        "avatars": {
          "small": "https://img3.doubanio.com/view/celebrity/s_ratio_celebrity/public/p29610.jpg",
          "large": "https://img3.doubanio.com/view/celebrity/s_ratio_celebrity/public/p29610.jpg",
          "medium": "https://img3.doubanio.com/view/celebrity/s_ratio_celebrity/public/p29610.jpg"
        },
        "name_en": "Peter Farrelly",
        "name": "彼得·法雷里",
        "alt": "https://movie.douban.com/celebrity/1036662/",
        "id": "1036662"
      }
    ],
    "pubdates": [
      "2018-09-11(多伦多电影节)",
      "2018-11-16(美国)",
      "2019-03-01(中国大陆)"
    ],
    "year": "2018",
    "images": {
      "small": "https://img3.doubanio.com/view/photo/s_ratio_poster/public/p2549177902.jpg",
      "large": "https://img3.doubanio.com/view/photo/s_ratio_poster/public/p2549177902.jpg",
      "medium": "https://img3.doubanio.com/view/photo/s_ratio_poster/public/p2549177902.jpg"
    },
    "alt": "https://movie.douban.com/subject/27060077/",
    "id": "27060077"
  },
  {
    "rating": {
      "max": 10,
      "average": 8.7,
      "details": {
        "1": 107.0,
        "3": 6293.0,
        "2": 708.0,
        "5": 28069.0,
        "4": 21282.0
      },
      "stars": "45",
      "min": 0
    },
    "genres": [
      "剧情",
      "传记",
      "音乐"
    ],
    "title": "波西米亚狂想曲",
    "casts": [
      {
        "avatars": {
          "small": "https://img3.doubanio.com/view/celebrity/s_ratio_celebrity/public/p1860.jpg",
          "large": "https://img3.doubanio.com/view/celebrity/s_ratio_celebrity/public/p1860.jpg",
          "medium": "https://img3.doubanio.com/view/celebrity/s_ratio_celebrity/public/p1860.jpg"
        },
        "name_en": "Rami Malek",
        "name": "拉米·马雷克",
        "alt": "https://movie.douban.com/celebrity/1044903/",
        "id": "1044903"
      },
      {
        "avatars": {
          "small": "https://img3.doubanio.com/view/celebrity/s_ratio_celebrity/public/p1548177691.13.jpg",
          "large": "https://img3.doubanio.com/view/celebrity/s_ratio_celebrity/public/p1548177691.13.jpg",
          "medium": "https://img3.doubanio.com/view/celebrity/s_ratio_celebrity/public/p1548177691.13.jpg"
        },
        "name_en": "Ben Hardy",
        "name": "本·哈迪",
        "alt": "https://movie.douban.com/celebrity/1344763/",
        "id": "1344763"
      },
      {
        "avatars": {
          "small": "https://img3.doubanio.com/view/celebrity/s_ratio_celebrity/public/p13772.jpg",
          "large": "https://img3.doubanio.com/view/celebrity/s_ratio_celebrity/public/p13772.jpg",
          "medium": "https://img3.doubanio.com/view/celebrity/s_ratio_celebrity/public/p13772.jpg"
        },
        "name_en": "Joseph Mazzello",
        "name": "约瑟夫·梅泽罗",
        "alt": "https://movie.douban.com/celebrity/1049517/",
        "id": "1049517"
      }
    ],
    "durations": [
      "135分钟",
      "131分钟(中国大陆)"
    ],
    "collect_count": 231198,
    "mainland_pubdate": "2019-03-22",
    "has_video": false,
    "original_title": "Bohemian Rhapsody",
    "subtype": "movie",
    "directors": [
      {
        "avatars": {
          "small": "https://img3.doubanio.com/view/celebrity/s_ratio_celebrity/public/p1403264395.93.jpg",
          "large": "https://img3.doubanio.com/view/celebrity/s_ratio_celebrity/public/p1403264395.93.jpg",
          "medium": "https://img3.doubanio.com/view/celebrity/s_ratio_celebrity/public/p1403264395.93.jpg"
        },
        "name_en": "Bryan Singer",
        "name": "布莱恩·辛格",
        "alt": "https://movie.douban.com/celebrity/1049586/",
        "id": "1049586"
      }
    ],
    "pubdates": [
      "2018-11-02(美国)",
      "2019-03-22(中国大陆)"
    ],
    "year": "2018",
    "images": {
      "small": "https://img3.doubanio.com/view/photo/s_ratio_poster/public/p2549558913.jpg",
      "large": "https://img3.doubanio.com/view/photo/s_ratio_poster/public/p2549558913.jpg",
      "medium": "https://img3.doubanio.com/view/photo/s_ratio_poster/public/p2549558913.jpg"
    },
    "alt": "https://movie.douban.com/subject/5300054/",
    "id": "5300054"
  },
  {
    "rating": {
      "max": 10,
      "average": 7.9,
      "details": {
        "1": 164.0,
        "3": 3844.0,
        "2": 620.0,
        "5": 5104.0,
        "4": 8518.0
      },
      "stars": "40",
      "min": 0
    },
    "genres": [
      "剧情",
      "家庭"
    ],
    "title": "地久天长",
    "casts": [
      {
        "avatars": {
          "small": "https://img3.doubanio.com/view/celebrity/s_ratio_celebrity/public/p12560.jpg",
          "large": "https://img3.doubanio.com/view/celebrity/s_ratio_celebrity/public/p12560.jpg",
          "medium": "https://img3.doubanio.com/view/celebrity/s_ratio_celebrity/public/p12560.jpg"
        },
        "name_en": "Jingchun Wang",
        "name": "王景春",
        "alt": "https://movie.douban.com/celebrity/1275934/",
        "id": "1275934"
      },
      {
        "avatars": {
          "small": "https://img3.doubanio.com/view/celebrity/s_ratio_celebrity/public/p1469426474.73.jpg",
          "large": "https://img3.doubanio.com/view/celebrity/s_ratio_celebrity/public/p1469426474.73.jpg",
          "medium": "https://img3.doubanio.com/view/celebrity/s_ratio_celebrity/public/p1469426474.73.jpg"
        },
        "name_en": "Mei Yong",
        "name": "咏梅",
        "alt": "https://movie.douban.com/celebrity/1276041/",
        "id": "1276041"
      },
      {
        "avatars": {
          "small": "https://img3.doubanio.com/view/celebrity/s_ratio_celebrity/public/p43726.jpg",
          "large": "https://img3.doubanio.com/view/celebrity/s_ratio_celebrity/public/p43726.jpg",
          "medium": "https://img3.doubanio.com/view/celebrity/s_ratio_celebrity/public/p43726.jpg"
        },
        "name_en": "Xi Qi",
        "name": "齐溪",
        "alt": "https://movie.douban.com/celebrity/1318634/",
        "id": "1318634"
      }
    ],
    "durations": [
      "175分钟"
    ],
    "collect_count": 78189,
    "mainland_pubdate": "2019-03-22",
    "has_video": false,
    "original_title": "地久天长",
    "subtype": "movie",
    "directors": [
      {
        "avatars": {
          "small": "https://img3.doubanio.com/view/celebrity/s_ratio_celebrity/public/p1553157534.76.jpg",
          "large": "https://img3.doubanio.com/view/celebrity/s_ratio_celebrity/public/p1553157534.76.jpg",
          "medium": "https://img3.doubanio.com/view/celebrity/s_ratio_celebrity/public/p1553157534.76.jpg"
        },
        "name_en": "Xiaoshuai Wang",
        "name": "王小帅",
        "alt": "https://movie.douban.com/celebrity/1018708/",
        "id": "1018708"
      }
    ],
    "pubdates": [
      "2019-02-14(柏林电影节)",
      "2019-03-22(中国大陆)"
    ],
    "year": "2019",
    "images": {
      "small": "https://img1.doubanio.com/view/photo/s_ratio_poster/public/p2550208359.jpg",
      "large": "https://img1.doubanio.com/view/photo/s_ratio_poster/public/p2550208359.jpg",
      "medium": "https://img1.doubanio.com/view/photo/s_ratio_poster/public/p2550208359.jpg"
    },
    "alt": "https://movie.douban.com/subject/26715636/",
    "id": "26715636"
  },
  {
    "rating": {
      "max": 10,
      "average": 5.6,
      "details": {
        "1": 42.0,
        "3": 256.0,
        "2": 118.0,
        "5": 13.0,
        "4": 75.0
      },
      "stars": "30",
      "min": 0
    },
    "genres": [
      "喜剧",
      "惊悚"
    ],
    "title": "狂暴凶狮",
    "casts": [
      {
        "avatars": {
          "small": "https://img3.doubanio.com/view/celebrity/s_ratio_celebrity/public/p1539943142.4.jpg",
          "large": "https://img3.doubanio.com/view/celebrity/s_ratio_celebrity/public/p1539943142.4.jpg",
          "medium": "https://img3.doubanio.com/view/celebrity/s_ratio_celebrity/public/p1539943142.4.jpg"
        },
        "name_en": "Sophie van Winden",
        "name": "索菲·范·德温",
        "alt": "https://movie.douban.com/celebrity/1242726/",
        "id": "1242726"
      },
      {
        "avatars": {
          "small": "https://img3.doubanio.com/view/celebrity/s_ratio_celebrity/public/p43801.jpg",
          "large": "https://img3.doubanio.com/view/celebrity/s_ratio_celebrity/public/p43801.jpg",
          "medium": "https://img3.doubanio.com/view/celebrity/s_ratio_celebrity/public/p43801.jpg"
        },
        "name_en": "Abbey Hoes",
        "name": "艾比·侯斯",
        "alt": "https://movie.douban.com/celebrity/1264266/",
        "id": "1264266"
      },
      {
        "avatars": {
          "small": "https://img1.doubanio.com/view/celebrity/s_ratio_celebrity/public/p1507792229.58.jpg",
          "large": "https://img1.doubanio.com/view/celebrity/s_ratio_celebrity/public/p1507792229.58.jpg",
          "medium": "https://img1.doubanio.com/view/celebrity/s_ratio_celebrity/public/p1507792229.58.jpg"
        },
        "name_en": "Britte Lagcher",
        "name": "布里特·拉格尔",
        "alt": "https://movie.douban.com/celebrity/1382415/",
        "id": "1382415"
      }
    ],
    "durations": [
      "105分钟"
    ],
    "collect_count": 4135,
    "mainland_pubdate": "2019-03-22",
    "has_video": false,
    "original_title": "Prooi",
    "subtype": "movie",
    "directors": [
      {
        "avatars": {
          "small": "https://img3.doubanio.com/view/celebrity/s_ratio_celebrity/public/p1360948259.53.jpg",
          "large": "https://img3.doubanio.com/view/celebrity/s_ratio_celebrity/public/p1360948259.53.jpg",
          "medium": "https://img3.doubanio.com/view/celebrity/s_ratio_celebrity/public/p1360948259.53.jpg"
        },
        "name_en": "Dick Maas",
        "name": "迪克·麦斯",
        "alt": "https://movie.douban.com/celebrity/1002933/",
        "id": "1002933"
      }
    ],
    "pubdates": [
      "2016-10-13(荷兰)",
      "2019-03-22(中国大陆)"
    ],
    "year": "2016",
    "images": {
      "small": "https://img3.doubanio.com/view/photo/s_ratio_poster/public/p2548549246.jpg",
      "large": "https://img3.doubanio.com/view/photo/s_ratio_poster/public/p2548549246.jpg",
      "medium": "https://img3.doubanio.com/view/photo/s_ratio_poster/public/p2548549246.jpg"
    },
    "alt": "https://movie.douban.com/subject/27150225/",
    "id": "27150225"
  },
  {
    "rating": {
      "max": 10,
      "average": 8.0,
      "details": {
        "1": 4226.0,
        "3": 35550.0,
        "2": 7526.0,
        "5": 60324.0,
        "4": 64703.0
      },
      "stars": "40",
      "min": 0
    },
    "genres": [
      "科幻",
      "灾难"
    ],
    "title": "流浪地球",
    "casts": [
      {
        "avatars": {
          "small": "https://img3.doubanio.com/view/celebrity/s_ratio_celebrity/public/p1533348792.03.jpg",
          "large": "https://img3.doubanio.com/view/celebrity/s_ratio_celebrity/public/p1533348792.03.jpg",
          "medium": "https://img3.doubanio.com/view/celebrity/s_ratio_celebrity/public/p1533348792.03.jpg"
        },
        "name_en": "Chuxiao Qu",
        "name": "屈楚萧",
        "alt": "https://movie.douban.com/celebrity/1359081/",
        "id": "1359081"
      },
      {
        "avatars": {
          "small": "https://img3.doubanio.com/view/celebrity/s_ratio_celebrity/public/p1549645325.74.jpg",
          "large": "https://img3.doubanio.com/view/celebrity/s_ratio_celebrity/public/p1549645325.74.jpg",
          "medium": "https://img3.doubanio.com/view/celebrity/s_ratio_celebrity/public/p1549645325.74.jpg"
        },
        "name_en": "Jing Wu",
        "name": "吴京",
        "alt": "https://movie.douban.com/celebrity/1000525/",
        "id": "1000525"
      },
      {
        "avatars": {
          "small": "https://img3.doubanio.com/view/celebrity/s_ratio_celebrity/public/p1540619056.43.jpg",
          "large": "https://img3.doubanio.com/view/celebrity/s_ratio_celebrity/public/p1540619056.43.jpg",
          "medium": "https://img3.doubanio.com/view/celebrity/s_ratio_celebrity/public/p1540619056.43.jpg"
        },
        "name_en": "Guangjie Li",
        "name": "李光洁",
        "alt": "https://movie.douban.com/celebrity/1275178/",
        "id": "1275178"
      }
    ],
    "durations": [
      "125分钟"
    ],
    "collect_count": 1610321,
    "mainland_pubdate": "2019-02-05",
    "has_video": false,
    "original_title": "流浪地球",
    "subtype": "movie",
    "directors": [
      {
        "avatars": {
          "small": "https://img3.doubanio.com/view/celebrity/s_ratio_celebrity/public/p1536678787.83.jpg",
          "large": "https://img3.doubanio.com/view/celebrity/s_ratio_celebrity/public/p1536678787.83.jpg",
          "medium": "https://img3.doubanio.com/view/celebrity/s_ratio_celebrity/public/p1536678787.83.jpg"
        },
        "name_en": "Frant Gwo",
        "name": "郭帆",
        "alt": "https://movie.douban.com/celebrity/1276086/",
        "id": "1276086"
      }
    ],
    "pubdates": [
      "2019-02-05(中国大陆)"
    ],
    "year": "2019",
    "images": {
      "small": "https://img3.doubanio.com/view/photo/s_ratio_poster/public/p2545472803.jpg",
      "large": "https://img3.doubanio.com/view/photo/s_ratio_poster/public/p2545472803.jpg",
      "medium": "https://img3.doubanio.com/view/photo/s_ratio_poster/public/p2545472803.jpg"
    },
    "alt": "https://movie.douban.com/subject/26266893/",
    "id": "26266893"
  },
  {
    "rating": {
      "max": 10,
      "average": 5.5,
      "details": {
        "1": 9.0,
        "3": 119.0,
        "2": 72.0,
        "5": 3.0,
        "4": 31.0
      },
      "stars": "30",
      "min": 0
    },
    "genres": [
      "剧情",
      "惊悚"
    ],
    "title": "警告",
    "casts": [
      {
        "avatars": {
          "small": "https://img1.doubanio.com/view/celebrity/s_ratio_celebrity/public/p21967.jpg",
          "large": "https://img1.doubanio.com/view/celebrity/s_ratio_celebrity/public/p21967.jpg",
          "medium": "https://img1.doubanio.com/view/celebrity/s_ratio_celebrity/public/p21967.jpg"
        },
        "name_en": "Raúl Arévalo",
        "name": "劳尔·阿雷瓦洛",
        "alt": "https://movie.douban.com/celebrity/1041807/",
        "id": "1041807"
      },
      {
        "avatars": {
          "small": "https://img3.doubanio.com/view/celebrity/s_ratio_celebrity/public/p1389435967.76.jpg",
          "large": "https://img3.doubanio.com/view/celebrity/s_ratio_celebrity/public/p1389435967.76.jpg",
          "medium": "https://img3.doubanio.com/view/celebrity/s_ratio_celebrity/public/p1389435967.76.jpg"
        },
        "name_en": "Aura Garrido",
        "name": "奥拉·加里多",
        "alt": "https://movie.douban.com/celebrity/1265576/",
        "id": "1265576"
      },
      {
        "avatars": {
          "small": "https://img3.doubanio.com/view/celebrity/s_ratio_celebrity/public/p1535015907.03.jpg",
          "large": "https://img3.doubanio.com/view/celebrity/s_ratio_celebrity/public/p1535015907.03.jpg",
          "medium": "https://img3.doubanio.com/view/celebrity/s_ratio_celebrity/public/p1535015907.03.jpg"
        },
        "name_en": "Hugo Arbues",
        "name": "雨果·阿布斯",
        "alt": "https://movie.douban.com/celebrity/1399727/",
        "id": "1399727"
      }
    ],
    "durations": [
      "92分钟"
    ],
    "collect_count": 1532,
    "mainland_pubdate": "2019-03-29",
    "has_video": false,
    "original_title": "El aviso",
    "subtype": "movie",
    "directors": [
      {
        "avatars": {
          "small": "https://img3.doubanio.com/view/celebrity/s_ratio_celebrity/public/p1516934387.21.jpg",
          "large": "https://img3.doubanio.com/view/celebrity/s_ratio_celebrity/public/p1516934387.21.jpg",
          "medium": "https://img3.doubanio.com/view/celebrity/s_ratio_celebrity/public/p1516934387.21.jpg"
        },
        "name_en": "Daniel Calparsoro",
        "name": "丹尼尔·卡尔帕索罗",
        "alt": "https://movie.douban.com/celebrity/1279913/",
        "id": "1279913"
      }
    ],
    "pubdates": [
      "2018-03-23(西班牙)",
      "2019-03-29(中国大陆)"
    ],
    "year": "2018",
    "images": {
      "small": "https://img3.doubanio.com/view/photo/s_ratio_poster/public/p2551888133.jpg",
      "large": "https://img3.doubanio.com/view/photo/s_ratio_poster/public/p2551888133.jpg",
      "medium": "https://img3.doubanio.com/view/photo/s_ratio_poster/public/p2551888133.jpg"
    },
    "alt": "https://movie.douban.com/subject/27132728/",
    "id": "27132728"
  },
  {
    "rating": {
      "max": 10,
      "average": 0,
      "details": {
        "1": 0,
        "3": 0,
        "2": 0,
        "5": 0,
        "4": 0
      },
      "stars": "00",
      "min": 0
    },
    "genres": [
      "惊悚",
      "恐怖"
    ],
    "title": "夜伴歌声",
    "casts": [
      {
        "avatars": {
          "small": "https://img3.doubanio.com/view/celebrity/s_ratio_celebrity/public/p1527750676.4.jpg",
          "large": "https://img3.doubanio.com/view/celebrity/s_ratio_celebrity/public/p1527750676.4.jpg",
          "medium": "https://img3.doubanio.com/view/celebrity/s_ratio_celebrity/public/p1527750676.4.jpg"
        },
        "name_en": "Li-er Mei",
        "name": "梅俪儿",
        "alt": "https://movie.douban.com/celebrity/1349852/",
        "id": "1349852"
      },
      {
        "avatars": {
          "small": "https://img1.doubanio.com/view/celebrity/s_ratio_celebrity/public/p1545534346.28.jpg",
          "large": "https://img1.doubanio.com/view/celebrity/s_ratio_celebrity/public/p1545534346.28.jpg",
          "medium": "https://img1.doubanio.com/view/celebrity/s_ratio_celebrity/public/p1545534346.28.jpg"
        },
        "name_en": "Zeyu Li",
        "name": "李泽宇",
        "alt": "https://movie.douban.com/celebrity/1407481/",
        "id": "1407481"
      },
      {
        "avatars": {
          "small": "https://img1.doubanio.com/f/movie/ca527386eb8c4e325611e22dfcb04cc116d6b423/pics/movie/celebrity-default-small.png",
          "large": "https://img3.doubanio.com/f/movie/63acc16ca6309ef191f0378faf793d1096a3e606/pics/movie/celebrity-default-large.png",
          "medium": "https://img1.doubanio.com/f/movie/8dd0c794499fe925ae2ae89ee30cd225750457b4/pics/movie/celebrity-default-medium.png"
        },
        "name_en": "Hexi Cao",
        "name": "曹鹤夕",
        "alt": "https://movie.douban.com/celebrity/1411266/",
        "id": "1411266"
      }
    ],
    "durations": [
      "86分钟"
    ],
    "collect_count": 271,
    "mainland_pubdate": "2019-03-22",
    "has_video": false,
    "original_title": "夜伴歌声",
    "subtype": "movie",
    "directors": [
      {
        "avatars": {
          "small": "https://img1.doubanio.com/view/celebrity/s_ratio_celebrity/public/p1490348628.29.jpg",
          "large": "https://img1.doubanio.com/view/celebrity/s_ratio_celebrity/public/p1490348628.29.jpg",
          "medium": "https://img1.doubanio.com/view/celebrity/s_ratio_celebrity/public/p1490348628.29.jpg"
        },
        "name_en": "Shilei Lu",
        "name": "陆诗雷",
        "alt": "https://movie.douban.com/celebrity/1360707/",
        "id": "1360707"
      }
    ],
    "pubdates": [
      "2019-03-22(中国大陆)"
    ],
    "year": "2019",
    "images": {
      "small": "https://img3.doubanio.com/view/photo/s_ratio_poster/public/p2548652745.jpg",
      "large": "https://img3.doubanio.com/view/photo/s_ratio_poster/public/p2548652745.jpg",
      "medium": "https://img3.doubanio.com/view/photo/s_ratio_poster/public/p2548652745.jpg"
    },
    "alt": "https://movie.douban.com/subject/30464313/",
    "id": "30464313"
  },
  {
    "rating": {
      "max": 10,
      "average": 4.5,
      "details": {
        "1": 47.0,
        "3": 61.0,
        "2": 115.0,
        "5": 6.0,
        "4": 17.0
      },
      "stars": "25",
      "min": 0
    },
    "genres": [
      "动作"
    ],
    "title": "三重威胁之跨国大营救",
    "casts": [
      {
        "avatars": {
          "small": "https://img3.doubanio.com/view/celebrity/s_ratio_celebrity/public/p1372859561.13.jpg",
          "large": "https://img3.doubanio.com/view/celebrity/s_ratio_celebrity/public/p1372859561.13.jpg",
          "medium": "https://img3.doubanio.com/view/celebrity/s_ratio_celebrity/public/p1372859561.13.jpg"
        },
        "name_en": "Tiger Hu Chen",
        "name": "陈虎",
        "alt": "https://movie.douban.com/celebrity/1280577/",
        "id": "1280577"
      },
      {
        "avatars": {
          "small": "https://img3.doubanio.com/view/celebrity/s_ratio_celebrity/public/p1501497925.32.jpg",
          "large": "https://img3.doubanio.com/view/celebrity/s_ratio_celebrity/public/p1501497925.32.jpg",
          "medium": "https://img3.doubanio.com/view/celebrity/s_ratio_celebrity/public/p1501497925.32.jpg"
        },
        "name_en": "Celina Jade",
        "name": "卢靖姗",
        "alt": "https://movie.douban.com/celebrity/1018743/",
        "id": "1018743"
      },
      {
        "avatars": {
          "small": "https://img3.doubanio.com/view/celebrity/s_ratio_celebrity/public/p1551081327.23.jpg",
          "large": "https://img3.doubanio.com/view/celebrity/s_ratio_celebrity/public/p1551081327.23.jpg",
          "medium": "https://img3.doubanio.com/view/celebrity/s_ratio_celebrity/public/p1551081327.23.jpg"
        },
        "name_en": "Tony Jaa",
        "name": "托尼·贾",
        "alt": "https://movie.douban.com/celebrity/1004643/",
        "id": "1004643"
      }
    ],
    "durations": [
      "96分钟"
    ],
    "collect_count": 1541,
    "mainland_pubdate": "2019-03-29",
    "has_video": true,
    "original_title": "Triple Threat",
    "subtype": "movie",
    "directors": [
      {
        "avatars": {
          "small": "https://img3.doubanio.com/view/celebrity/s_ratio_celebrity/public/p1501464004.21.jpg",
          "large": "https://img3.doubanio.com/view/celebrity/s_ratio_celebrity/public/p1501464004.21.jpg",
          "medium": "https://img3.doubanio.com/view/celebrity/s_ratio_celebrity/public/p1501464004.21.jpg"
        },
        "name_en": "Jesse V. Johnson",
        "name": "杰西·约翰逊",
        "alt": "https://movie.douban.com/celebrity/1103525/",
        "id": "1103525"
      }
    ],
    "pubdates": [
      "2019-03-19(美国)",
      "2019-03-29(中国大陆)"
    ],
    "year": "2019",
    "images": {
      "small": "https://img3.doubanio.com/view/photo/s_ratio_poster/public/p2551252121.jpg",
      "large": "https://img3.doubanio.com/view/photo/s_ratio_poster/public/p2551252121.jpg",
      "medium": "https://img3.doubanio.com/view/photo/s_ratio_poster/public/p2551252121.jpg"
    },
    "alt": "https://movie.douban.com/subject/26909787/",
    "id": "26909787"
  },
  {
    "rating": {
      "max": 10,
      "average": 6.9,
      "details": {
        "1": 12.0,
        "3": 736.0,
        "2": 118.0,
        "5": 133.0,
        "4": 526.0
      },
      "stars": "35",
      "min": 0
    },
    "genres": [
      "喜剧",
      "动画",
      "冒险"
    ],
    "title": "乐高大电影2",
    "casts": [
      {
        "avatars": {
          "small": "https://img3.doubanio.com/view/celebrity/s_ratio_celebrity/public/p1408711300.32.jpg",
          "large": "https://img3.doubanio.com/view/celebrity/s_ratio_celebrity/public/p1408711300.32.jpg",
          "medium": "https://img3.doubanio.com/view/celebrity/s_ratio_celebrity/public/p1408711300.32.jpg"
        },
        "name_en": "Chris Pratt",
        "name": "克里斯·帕拉特",
        "alt": "https://movie.douban.com/celebrity/1017967/",
        "id": "1017967"
      },
      {
        "avatars": {
          "small": "https://img1.doubanio.com/view/celebrity/s_ratio_celebrity/public/p22028.jpg",
          "large": "https://img1.doubanio.com/view/celebrity/s_ratio_celebrity/public/p22028.jpg",
          "medium": "https://img1.doubanio.com/view/celebrity/s_ratio_celebrity/public/p22028.jpg"
        },
        "name_en": "Elizabeth Banks",
        "name": "伊丽莎白·班克斯",
        "alt": "https://movie.douban.com/celebrity/1004571/",
        "id": "1004571"
      },
      {
        "avatars": {
          "small": "https://img1.doubanio.com/view/celebrity/s_ratio_celebrity/public/p7197.jpg",
          "large": "https://img1.doubanio.com/view/celebrity/s_ratio_celebrity/public/p7197.jpg",
          "medium": "https://img1.doubanio.com/view/celebrity/s_ratio_celebrity/public/p7197.jpg"
        },
        "name_en": "Will Arnett",
        "name": "威尔·阿奈特",
        "alt": "https://movie.douban.com/celebrity/1044709/",
        "id": "1044709"
      }
    ],
    "durations": [
      "106分钟"
    ],
    "collect_count": 5221,
    "mainland_pubdate": "2019-03-22",
    "has_video": false,
    "original_title": "The Lego Movie 2: The Second Part",
    "subtype": "movie",
    "directors": [
      {
        "avatars": {
          "small": "https://img3.doubanio.com/view/celebrity/s_ratio_celebrity/public/p1500863285.35.jpg",
          "large": "https://img3.doubanio.com/view/celebrity/s_ratio_celebrity/public/p1500863285.35.jpg",
          "medium": "https://img3.doubanio.com/view/celebrity/s_ratio_celebrity/public/p1500863285.35.jpg"
        },
        "name_en": "Mike Mitchell",
        "name": "迈克·米切尔",
        "alt": "https://movie.douban.com/celebrity/1292230/",
        "id": "1292230"
      }
    ],
    "pubdates": [
      "2019-02-08(美国)",
      "2019-03-22(中国大陆)"
    ],
    "year": "2019",
    "images": {
      "small": "https://img3.doubanio.com/view/photo/s_ratio_poster/public/p2549353234.jpg",
      "large": "https://img3.doubanio.com/view/photo/s_ratio_poster/public/p2549353234.jpg",
      "medium": "https://img3.doubanio.com/view/photo/s_ratio_poster/public/p2549353234.jpg"
    },
    "alt": "https://movie.douban.com/subject/25833233/",
    "id": "25833233"
  },
  {
    "rating": {
      "max": 10,
      "average": 7.6,
      "details": {
        "1": 513.0,
        "3": 19207.0,
        "2": 2802.0,
        "5": 13614.0,
        "4": 27916.0
      },
      "stars": "40",
      "min": 0
    },
    "genres": [
      "动作",
      "科幻",
      "冒险"
    ],
    "title": "阿丽塔：战斗天使",
    "casts": [
      {
        "avatars": {
          "small": "https://img3.doubanio.com/view/celebrity/s_ratio_celebrity/public/p1501911452.02.jpg",
          "large": "https://img3.doubanio.com/view/celebrity/s_ratio_celebrity/public/p1501911452.02.jpg",
          "medium": "https://img3.doubanio.com/view/celebrity/s_ratio_celebrity/public/p1501911452.02.jpg"
        },
        "name_en": "Rosa Salazar",
        "name": "罗莎·萨拉查",
        "alt": "https://movie.douban.com/celebrity/1342762/",
        "id": "1342762"
      },
      {
        "avatars": {
          "small": "https://img3.doubanio.com/view/celebrity/s_ratio_celebrity/public/p26974.jpg",
          "large": "https://img3.doubanio.com/view/celebrity/s_ratio_celebrity/public/p26974.jpg",
          "medium": "https://img3.doubanio.com/view/celebrity/s_ratio_celebrity/public/p26974.jpg"
        },
        "name_en": "Christoph Waltz",
        "name": "克里斯托弗·沃尔兹",
        "alt": "https://movie.douban.com/celebrity/1054405/",
        "id": "1054405"
      },
      {
        "avatars": {
          "small": "https://img3.doubanio.com/view/celebrity/s_ratio_celebrity/public/p1549880660.24.jpg",
          "large": "https://img3.doubanio.com/view/celebrity/s_ratio_celebrity/public/p1549880660.24.jpg",
          "medium": "https://img3.doubanio.com/view/celebrity/s_ratio_celebrity/public/p1549880660.24.jpg"
        },
        "name_en": "Keean Johnson",
        "name": "基恩·约翰逊",
        "alt": "https://movie.douban.com/celebrity/1399007/",
        "id": "1399007"
      }
    ],
    "durations": [
      "122分钟"
    ],
    "collect_count": 367906,
    "mainland_pubdate": "2019-02-22",
    "has_video": false,
    "original_title": "Alita: Battle Angel",
    "subtype": "movie",
    "directors": [
      {
        "avatars": {
          "small": "https://img1.doubanio.com/view/celebrity/s_ratio_celebrity/public/p1378050540.89.jpg",
          "large": "https://img1.doubanio.com/view/celebrity/s_ratio_celebrity/public/p1378050540.89.jpg",
          "medium": "https://img1.doubanio.com/view/celebrity/s_ratio_celebrity/public/p1378050540.89.jpg"
        },
        "name_en": "Robert Rodriguez",
        "name": "罗伯特·罗德里格兹",
        "alt": "https://movie.douban.com/celebrity/1019016/",
        "id": "1019016"
      }
    ],
    "pubdates": [
      "2019-02-05(台湾)",
      "2019-02-14(美国)",
      "2019-02-22(中国大陆)"
    ],
    "year": "2019",
    "images": {
      "small": "https://img3.doubanio.com/view/photo/s_ratio_poster/public/p2544987866.jpg",
      "large": "https://img3.doubanio.com/view/photo/s_ratio_poster/public/p2544987866.jpg",
      "medium": "https://img3.doubanio.com/view/photo/s_ratio_poster/public/p2544987866.jpg"
    },
    "alt": "https://movie.douban.com/subject/1652592/",
    "id": "1652592"
  },
  {
    "rating": {
      "max": 10,
      "average": 7.5,
      "details": {
        "1": 79.0,
        "3": 7031.0,
        "2": 718.0,
        "5": 3892.0,
        "4": 9446.0
      },
      "stars": "40",
      "min": 0
    },
    "genres": [
      "动画",
      "奇幻",
      "冒险"
    ],
    "title": "驯龙高手3",
    "casts": [
      {
        "avatars": {
          "small": "https://img3.doubanio.com/view/celebrity/s_ratio_celebrity/public/p893.jpg",
          "large": "https://img3.doubanio.com/view/celebrity/s_ratio_celebrity/public/p893.jpg",
          "medium": "https://img3.doubanio.com/view/celebrity/s_ratio_celebrity/public/p893.jpg"
        },
        "name_en": "Jay Baruchel",
        "name": "杰伊·巴鲁切尔",
        "alt": "https://movie.douban.com/celebrity/1002664/",
        "id": "1002664"
      },
      {
        "avatars": {
          "small": "https://img3.doubanio.com/view/celebrity/s_ratio_celebrity/public/p28644.jpg",
          "large": "https://img3.doubanio.com/view/celebrity/s_ratio_celebrity/public/p28644.jpg",
          "medium": "https://img3.doubanio.com/view/celebrity/s_ratio_celebrity/public/p28644.jpg"
        },
        "name_en": "America Ferrera",
        "name": "亚美莉卡·费雷拉",
        "alt": "https://movie.douban.com/celebrity/1000055/",
        "id": "1000055"
      },
      {
        "avatars": {
          "small": "https://img1.doubanio.com/view/celebrity/s_ratio_celebrity/public/p1425119644.17.jpg",
          "large": "https://img1.doubanio.com/view/celebrity/s_ratio_celebrity/public/p1425119644.17.jpg",
          "medium": "https://img1.doubanio.com/view/celebrity/s_ratio_celebrity/public/p1425119644.17.jpg"
        },
        "name_en": "F. Murray Abraham",
        "name": "F·默里·亚伯拉罕",
        "alt": "https://movie.douban.com/celebrity/1055073/",
        "id": "1055073"
      }
    ],
    "durations": [
      "104分钟"
    ],
    "collect_count": 118554,
    "mainland_pubdate": "2019-03-01",
    "has_video": false,
    "original_title": "How To Train Your Dragon: The Hidden World",
    "subtype": "movie",
    "directors": [
      {
        "avatars": {
          "small": "https://img1.doubanio.com/view/celebrity/s_ratio_celebrity/public/p18169.jpg",
          "large": "https://img1.doubanio.com/view/celebrity/s_ratio_celebrity/public/p18169.jpg",
          "medium": "https://img1.doubanio.com/view/celebrity/s_ratio_celebrity/public/p18169.jpg"
        },
        "name_en": "Dean DeBlois",
        "name": "迪恩·德布洛斯",
        "alt": "https://movie.douban.com/celebrity/1018302/",
        "id": "1018302"
      }
    ],
    "pubdates": [
      "2019-01-03(澳大利亚)",
      "2019-02-22(美国)",
      "2019-03-01(中国大陆)"
    ],
    "year": "2019",
    "images": {
      "small": "https://img3.doubanio.com/view/photo/s_ratio_poster/public/p2546335362.jpg",
      "large": "https://img3.doubanio.com/view/photo/s_ratio_poster/public/p2546335362.jpg",
      "medium": "https://img3.doubanio.com/view/photo/s_ratio_poster/public/p2546335362.jpg"
    },
    "alt": "https://movie.douban.com/subject/19899707/",
    "id": "19899707"
  },
  {
    "rating": {
      "max": 10,
      "average": 0,
      "details": {
        "1": 0,
        "3": 0,
        "2": 0,
        "5": 0,
        "4": 0
      },
      "stars": "00",
      "min": 0
    },
    "genres": [
      "悬疑",
      "惊悚"
    ],
    "title": "劫数难逃",
    "casts": [
      {
        "avatars": {
          "small": "https://img1.doubanio.com/view/celebrity/s_ratio_celebrity/public/p1418815553.39.jpg",
          "large": "https://img1.doubanio.com/view/celebrity/s_ratio_celebrity/public/p1418815553.39.jpg",
          "medium": "https://img1.doubanio.com/view/celebrity/s_ratio_celebrity/public/p1418815553.39.jpg"
        },
        "name_en": "Yuxin Yao",
        "name": "姚雨鑫",
        "alt": "https://movie.douban.com/celebrity/1336951/",
        "id": "1336951"
      },
      {
        "avatars": {
          "small": "https://img3.doubanio.com/view/celebrity/s_ratio_celebrity/public/p1505271666.55.jpg",
          "large": "https://img3.doubanio.com/view/celebrity/s_ratio_celebrity/public/p1505271666.55.jpg",
          "medium": "https://img3.doubanio.com/view/celebrity/s_ratio_celebrity/public/p1505271666.55.jpg"
        },
        "name_en": "Cynthia Gang",
        "name": "刚小希",
        "alt": "https://movie.douban.com/celebrity/1376439/",
        "id": "1376439"
      },
      {
        "avatars": {
          "small": "https://img1.doubanio.com/view/celebrity/s_ratio_celebrity/public/p1457345580.8.jpg",
          "large": "https://img1.doubanio.com/view/celebrity/s_ratio_celebrity/public/p1457345580.8.jpg",
          "medium": "https://img1.doubanio.com/view/celebrity/s_ratio_celebrity/public/p1457345580.8.jpg"
        },
        "name_en": "Senbao Lu",
        "name": "卢森堡",
        "alt": "https://movie.douban.com/celebrity/1355403/",
        "id": "1355403"
      }
    ],
    "durations": [
      "90分钟"
    ],
    "collect_count": 13,
    "mainland_pubdate": "2019-03-29",
    "has_video": false,
    "original_title": "劫数难逃",
    "subtype": "movie",
    "directors": [
      {
        "avatars": {
          "small": "https://img1.doubanio.com/f/movie/ca527386eb8c4e325611e22dfcb04cc116d6b423/pics/movie/celebrity-default-small.png",
          "large": "https://img3.doubanio.com/f/movie/63acc16ca6309ef191f0378faf793d1096a3e606/pics/movie/celebrity-default-large.png",
          "medium": "https://img1.doubanio.com/f/movie/8dd0c794499fe925ae2ae89ee30cd225750457b4/pics/movie/celebrity-default-medium.png"
        },
        "name_en": "",
        "name": "徐官祥",
        "alt": "https://movie.douban.com/celebrity/1413534/",
        "id": "1413534"
      },
      {
        "avatars": {
          "small": "https://img3.doubanio.com/view/celebrity/s_ratio_celebrity/public/p1484102270.46.jpg",
          "large": "https://img3.doubanio.com/view/celebrity/s_ratio_celebrity/public/p1484102270.46.jpg",
          "medium": "https://img3.doubanio.com/view/celebrity/s_ratio_celebrity/public/p1484102270.46.jpg"
        },
        "name_en": "Zhifeng Chen",
        "name": "陈志峰",
        "alt": "https://movie.douban.com/celebrity/1366905/",
        "id": "1366905"
      }
    ],
    "pubdates": [
      "2019-03-29(中国大陆)"
    ],
    "year": "2019",
    "images": {
      "small": "https://img3.doubanio.com/view/photo/s_ratio_poster/public/p2551118196.jpg",
      "large": "https://img3.doubanio.com/view/photo/s_ratio_poster/public/p2551118196.jpg",
      "medium": "https://img3.doubanio.com/view/photo/s_ratio_poster/public/p2551118196.jpg"
    },
    "alt": "https://movie.douban.com/subject/32489718/",
    "id": "32489718"
  },
  {
    "rating": {
      "max": 10,
      "average": 0,
      "details": {
        "1": 0,
        "3": 0,
        "2": 0,
        "5": 0,
        "4": 0
      },
      "stars": "00",
      "min": 0
    },
    "genres": [
      "剧情"
    ],
    "title": "似水流年",
    "casts": [
      {
        "avatars": {
          "small": "https://img3.doubanio.com/view/celebrity/s_ratio_celebrity/public/p1533109451.03.jpg",
          "large": "https://img3.doubanio.com/view/celebrity/s_ratio_celebrity/public/p1533109451.03.jpg",
          "medium": "https://img3.doubanio.com/view/celebrity/s_ratio_celebrity/public/p1533109451.03.jpg"
        },
        "name_en": "Kun Hu",
        "name": "胡琨",
        "alt": "https://movie.douban.com/celebrity/1372978/",
        "id": "1372978"
      },
      {
        "avatars": {
          "small": "https://img3.doubanio.com/view/celebrity/s_ratio_celebrity/public/p1464401597.86.jpg",
          "large": "https://img3.doubanio.com/view/celebrity/s_ratio_celebrity/public/p1464401597.86.jpg",
          "medium": "https://img3.doubanio.com/view/celebrity/s_ratio_celebrity/public/p1464401597.86.jpg"
        },
        "name_en": "Junchen Chu",
        "name": "初俊辰",
        "alt": "https://movie.douban.com/celebrity/1357954/",
        "id": "1357954"
      },
      {
        "avatars": {
          "small": "https://img3.doubanio.com/view/celebrity/s_ratio_celebrity/public/p1542877188.62.jpg",
          "large": "https://img3.doubanio.com/view/celebrity/s_ratio_celebrity/public/p1542877188.62.jpg",
          "medium": "https://img3.doubanio.com/view/celebrity/s_ratio_celebrity/public/p1542877188.62.jpg"
        },
        "name_en": "",
        "name": "李云赫",
        "alt": "https://movie.douban.com/celebrity/1405052/",
        "id": "1405052"
      }
    ],
    "durations": [
      "113分钟"
    ],
    "collect_count": 115,
    "mainland_pubdate": "2019-03-29",
    "has_video": false,
    "original_title": "似水流年",
    "subtype": "movie",
    "directors": [
      {
        "avatars": {
          "small": "https://img3.doubanio.com/view/celebrity/s_ratio_celebrity/public/p1542877148.4.jpg",
          "large": "https://img3.doubanio.com/view/celebrity/s_ratio_celebrity/public/p1542877148.4.jpg",
          "medium": "https://img3.doubanio.com/view/celebrity/s_ratio_celebrity/public/p1542877148.4.jpg"
        },
        "name_en": "",
        "name": "郑君奇",
        "alt": "https://movie.douban.com/celebrity/1405049/",
        "id": "1405049"
      },
      {
        "avatars": {
          "small": "https://img1.doubanio.com/view/celebrity/s_ratio_celebrity/public/p1542877161.07.jpg",
          "large": "https://img1.doubanio.com/view/celebrity/s_ratio_celebrity/public/p1542877161.07.jpg",
          "medium": "https://img1.doubanio.com/view/celebrity/s_ratio_celebrity/public/p1542877161.07.jpg"
        },
        "name_en": "",
        "name": "李龙俊",
        "alt": "https://movie.douban.com/celebrity/1405050/",
        "id": "1405050"
      }
    ],
    "pubdates": [
      "2019-03-29(中国大陆)"
    ],
    "year": "2019",
    "images": {
      "small": "https://img1.doubanio.com/view/photo/s_ratio_poster/public/p2551890738.jpg",
      "large": "https://img1.doubanio.com/view/photo/s_ratio_poster/public/p2551890738.jpg",
      "medium": "https://img1.doubanio.com/view/photo/s_ratio_poster/public/p2551890738.jpg"
    },
    "alt": "https://movie.douban.com/subject/30384186/",
    "id": "30384186"
  },
  {
    "rating": {
      "max": 10,
      "average": 0,
      "details": {
        "1": 0,
        "3": 0,
        "2": 0,
        "5": 0,
        "4": 0
      },
      "stars": "00",
      "min": 0
    },
    "genres": [
      "悬疑",
      "惊悚"
    ],
    "title": "少女宿舍",
    "casts": [
      {
        "avatars": {
          "small": "https://img3.doubanio.com/view/celebrity/s_ratio_celebrity/public/p1480920311.96.jpg",
          "large": "https://img3.doubanio.com/view/celebrity/s_ratio_celebrity/public/p1480920311.96.jpg",
          "medium": "https://img3.doubanio.com/view/celebrity/s_ratio_celebrity/public/p1480920311.96.jpg"
        },
        "name_en": "Lin Chen",
        "name": "陈淋",
        "alt": "https://movie.douban.com/celebrity/1365415/",
        "id": "1365415"
      },
      {
        "avatars": {
          "small": "https://img3.doubanio.com/view/celebrity/s_ratio_celebrity/public/p1553217835.21.jpg",
          "large": "https://img3.doubanio.com/view/celebrity/s_ratio_celebrity/public/p1553217835.21.jpg",
          "medium": "https://img3.doubanio.com/view/celebrity/s_ratio_celebrity/public/p1553217835.21.jpg"
        },
        "name_en": "Cao Yue",
        "name": "曹越",
        "alt": "https://movie.douban.com/celebrity/1411458/",
        "id": "1411458"
      },
      {
        "avatars": {
          "small": "https://img3.doubanio.com/view/celebrity/s_ratio_celebrity/public/p34082.jpg",
          "large": "https://img3.doubanio.com/view/celebrity/s_ratio_celebrity/public/p34082.jpg",
          "medium": "https://img3.doubanio.com/view/celebrity/s_ratio_celebrity/public/p34082.jpg"
        },
        "name_en": "Kai Man Tin",
        "name": "田启文",
        "alt": "https://movie.douban.com/celebrity/1315882/",
        "id": "1315882"
      }
    ],
    "durations": [
      "88分钟"
    ],
    "collect_count": 109,
    "mainland_pubdate": "2019-03-15",
    "has_video": false,
    "original_title": "少女宿舍",
    "subtype": "movie",
    "directors": [
      {
        "avatars": {
          "small": "https://img1.doubanio.com/view/celebrity/s_ratio_celebrity/public/p7708.jpg",
          "large": "https://img1.doubanio.com/view/celebrity/s_ratio_celebrity/public/p7708.jpg",
          "medium": "https://img1.doubanio.com/view/celebrity/s_ratio_celebrity/public/p7708.jpg"
        },
        "name_en": "Pan Pan Yeung",
        "name": "杨盼盼",
        "alt": "https://movie.douban.com/celebrity/1164633/",
        "id": "1164633"
      },
      {
        "avatars": {
          "small": "https://img1.doubanio.com/view/celebrity/s_ratio_celebrity/public/p1552543997.37.jpg",
          "large": "https://img1.doubanio.com/view/celebrity/s_ratio_celebrity/public/p1552543997.37.jpg",
          "medium": "https://img1.doubanio.com/view/celebrity/s_ratio_celebrity/public/p1552543997.37.jpg"
        },
        "name_en": "Shangshui Cao ",
        "name": "曹尚水",
        "alt": "https://movie.douban.com/celebrity/1411457/",
        "id": "1411457"
      }
    ],
    "pubdates": [
      "2019-03-15(中国大陆)"
    ],
    "year": "2019",
    "images": {
      "small": "https://img3.doubanio.com/view/photo/s_ratio_poster/public/p2550454042.jpg",
      "large": "https://img3.doubanio.com/view/photo/s_ratio_poster/public/p2550454042.jpg",
      "medium": "https://img3.doubanio.com/view/photo/s_ratio_poster/public/p2550454042.jpg"
    },
    "alt": "https://movie.douban.com/subject/30426150/",
    "id": "30426150"
  },
  {
    "rating": {
      "max": 10,
      "average": 5.7,
      "details": {
        "1": 4198.0,
        "3": 10495.0,
        "2": 7594.0,
        "5": 3159.0,
        "4": 5702.0
      },
      "stars": "30",
      "min": 0
    },
    "genres": [
      "剧情",
      "喜剧"
    ],
    "title": "新喜剧之王",
    "casts": [
      {
        "avatars": {
          "small": "https://img3.doubanio.com/view/celebrity/s_ratio_celebrity/public/p1356403251.95.jpg",
          "large": "https://img3.doubanio.com/view/celebrity/s_ratio_celebrity/public/p1356403251.95.jpg",
          "medium": "https://img3.doubanio.com/view/celebrity/s_ratio_celebrity/public/p1356403251.95.jpg"
        },
        "name_en": "Baoqiang Wang",
        "name": "王宝强",
        "alt": "https://movie.douban.com/celebrity/1274388/",
        "id": "1274388"
      },
      {
        "avatars": {
          "small": "https://img3.doubanio.com/view/celebrity/s_ratio_celebrity/public/p1546495999.54.jpg",
          "large": "https://img3.doubanio.com/view/celebrity/s_ratio_celebrity/public/p1546495999.54.jpg",
          "medium": "https://img3.doubanio.com/view/celebrity/s_ratio_celebrity/public/p1546495999.54.jpg"
        },
        "name_en": "Jingwen E",
        "name": "鄂靖文",
        "alt": "https://movie.douban.com/celebrity/1362292/",
        "id": "1362292"
      },
      {
        "avatars": {
          "small": "https://img1.doubanio.com/view/celebrity/s_ratio_celebrity/public/p1547695598.8.jpg",
          "large": "https://img1.doubanio.com/view/celebrity/s_ratio_celebrity/public/p1547695598.8.jpg",
          "medium": "https://img1.doubanio.com/view/celebrity/s_ratio_celebrity/public/p1547695598.8.jpg"
        },
        "name_en": "Quandan Zhang",
        "name": "张全蛋",
        "alt": "https://movie.douban.com/celebrity/1350283/",
        "id": "1350283"
      }
    ],
    "durations": [
      "91分钟"
    ],
    "collect_count": 249647,
    "mainland_pubdate": "2019-02-05",
    "has_video": true,
    "original_title": "新喜剧之王",
    "subtype": "movie",
    "directors": [
      {
        "avatars": {
          "small": "https://img3.doubanio.com/view/celebrity/s_ratio_celebrity/public/p47421.jpg",
          "large": "https://img3.doubanio.com/view/celebrity/s_ratio_celebrity/public/p47421.jpg",
          "medium": "https://img3.doubanio.com/view/celebrity/s_ratio_celebrity/public/p47421.jpg"
        },
        "name_en": "Stephen Chow",
        "name": "周星驰",
        "alt": "https://movie.douban.com/celebrity/1048026/",
        "id": "1048026"
      }
    ],
    "pubdates": [
      "2019-02-05(中国大陆)"
    ],
    "year": "2019",
    "images": {
      "small": "https://img3.doubanio.com/view/photo/s_ratio_poster/public/p2541240741.jpg",
      "large": "https://img3.doubanio.com/view/photo/s_ratio_poster/public/p2541240741.jpg",
      "medium": "https://img3.doubanio.com/view/photo/s_ratio_poster/public/p2541240741.jpg"
    },
    "alt": "https://movie.douban.com/subject/4840388/",
    "id": "4840388"
  },
  {
    "rating": {
      "max": 10,
      "average": 0,
      "details": {
        "1": 0,
        "3": 0,
        "2": 0,
        "5": 0,
        "4": 0
      },
      "stars": "00",
      "min": 0
    },
    "genres": [
      "剧情"
    ],
    "title": "醒来之爱的呼唤",
    "casts": [
      {
        "avatars": {
          "small": "https://img1.doubanio.com/view/celebrity/s_ratio_celebrity/public/p1550736625.49.jpg",
          "large": "https://img1.doubanio.com/view/celebrity/s_ratio_celebrity/public/p1550736625.49.jpg",
          "medium": "https://img1.doubanio.com/view/celebrity/s_ratio_celebrity/public/p1550736625.49.jpg"
        },
        "name_en": "Mengnan Li",
        "name": "李梦男",
        "alt": "https://movie.douban.com/celebrity/1321589/",
        "id": "1321589"
      },
      {
        "avatars": {
          "small": "https://img1.doubanio.com/view/celebrity/s_ratio_celebrity/public/p1550550645.28.jpg",
          "large": "https://img1.doubanio.com/view/celebrity/s_ratio_celebrity/public/p1550550645.28.jpg",
          "medium": "https://img1.doubanio.com/view/celebrity/s_ratio_celebrity/public/p1550550645.28.jpg"
        },
        "name_en": "Chen Zhang",
        "name": "张琛",
        "alt": "https://movie.douban.com/celebrity/1334751/",
        "id": "1334751"
      },
      {
        "avatars": {
          "small": "https://img3.doubanio.com/view/celebrity/s_ratio_celebrity/public/p1550736643.55.jpg",
          "large": "https://img3.doubanio.com/view/celebrity/s_ratio_celebrity/public/p1550736643.55.jpg",
          "medium": "https://img3.doubanio.com/view/celebrity/s_ratio_celebrity/public/p1550736643.55.jpg"
        },
        "name_en": "Chong Fu",
        "name": "傅冲",
        "alt": "https://movie.douban.com/celebrity/1318445/",
        "id": "1318445"
      }
    ],
    "durations": [
      "106分钟"
    ],
    "collect_count": 316,
    "mainland_pubdate": "2019-03-08",
    "has_video": false,
    "original_title": "醒来之爱的呼唤",
    "subtype": "movie",
    "directors": [
      {
        "avatars": {
          "small": "https://img3.doubanio.com/view/celebrity/s_ratio_celebrity/public/p1524885360.94.jpg",
          "large": "https://img3.doubanio.com/view/celebrity/s_ratio_celebrity/public/p1524885360.94.jpg",
          "medium": "https://img3.doubanio.com/view/celebrity/s_ratio_celebrity/public/p1524885360.94.jpg"
        },
        "name_en": "Lutao Wang",
        "name": "王陆涛",
        "alt": "https://movie.douban.com/celebrity/1391938/",
        "id": "1391938"
      }
    ],
    "pubdates": [
      "2019-03-08(中国大陆)"
    ],
    "year": "2019",
    "images": {
      "small": "https://img1.doubanio.com/view/photo/s_ratio_poster/public/p2549170039.jpg",
      "large": "https://img1.doubanio.com/view/photo/s_ratio_poster/public/p2549170039.jpg",
      "medium": "https://img1.doubanio.com/view/photo/s_ratio_poster/public/p2549170039.jpg"
    },
    "alt": "https://movie.douban.com/subject/30460368/",
    "id": "30460368"
  },
  {
    "rating": {
      "max": 10,
      "average": 7.2,
      "details": {
        "1": 35.0,
        "3": 1186.0,
        "2": 185.0,
        "5": 491.0,
        "4": 1143.0
      },
      "stars": "40",
      "min": 0
    },
    "genres": [
      "动作",
      "动画"
    ],
    "title": "我的英雄学院：两位英雄",
    "casts": [
      {
        "avatars": {
          "small": "https://img1.doubanio.com/view/celebrity/s_ratio_celebrity/public/p1490072678.98.jpg",
          "large": "https://img1.doubanio.com/view/celebrity/s_ratio_celebrity/public/p1490072678.98.jpg",
          "medium": "https://img1.doubanio.com/view/celebrity/s_ratio_celebrity/public/p1490072678.98.jpg"
        },
        "name_en": "Daiki Yamashita",
        "name": "山下大辉",
        "alt": "https://movie.douban.com/celebrity/1334753/",
        "id": "1334753"
      },
      {
        "avatars": {
          "small": "https://img3.doubanio.com/view/celebrity/s_ratio_celebrity/public/p23513.jpg",
          "large": "https://img3.doubanio.com/view/celebrity/s_ratio_celebrity/public/p23513.jpg",
          "medium": "https://img3.doubanio.com/view/celebrity/s_ratio_celebrity/public/p23513.jpg"
        },
        "name_en": "Kenta Miyake",
        "name": "三宅健太",
        "alt": "https://movie.douban.com/celebrity/1176990/",
        "id": "1176990"
      },
      {
        "avatars": {
          "small": "https://img1.doubanio.com/view/celebrity/s_ratio_celebrity/public/p47147.jpg",
          "large": "https://img1.doubanio.com/view/celebrity/s_ratio_celebrity/public/p47147.jpg",
          "medium": "https://img1.doubanio.com/view/celebrity/s_ratio_celebrity/public/p47147.jpg"
        },
        "name_en": "Mirai Shida",
        "name": "志田未来",
        "alt": "https://movie.douban.com/celebrity/1045964/",
        "id": "1045964"
      }
    ],
    "durations": [
      "96分钟"
    ],
    "collect_count": 19396,
    "mainland_pubdate": "2019-03-15",
    "has_video": false,
    "original_title": "僕のヒーローアカデミア THE MOVIE ～2人の英雄～",
    "subtype": "movie",
    "directors": [
      {
        "avatars": {
          "small": "https://img1.doubanio.com/view/celebrity/s_ratio_celebrity/public/p1498830911.08.jpg",
          "large": "https://img1.doubanio.com/view/celebrity/s_ratio_celebrity/public/p1498830911.08.jpg",
          "medium": "https://img1.doubanio.com/view/celebrity/s_ratio_celebrity/public/p1498830911.08.jpg"
        },
        "name_en": "Kenji Nagasaki",
        "name": "长崎健司",
        "alt": "https://movie.douban.com/celebrity/1360038/",
        "id": "1360038"
      }
    ],
    "pubdates": [
      "2018-08-03(日本)",
      "2019-03-15(中国大陆)"
    ],
    "year": "2018",
    "images": {
      "small": "https://img1.doubanio.com/view/photo/s_ratio_poster/public/p2548783889.jpg",
      "large": "https://img1.doubanio.com/view/photo/s_ratio_poster/public/p2548783889.jpg",
      "medium": "https://img1.doubanio.com/view/photo/s_ratio_poster/public/p2548783889.jpg"
    },
    "alt": "https://movie.douban.com/subject/27602116/",
    "id": "27602116"
  }
]